nextline_test_utils/__about__.py
nextline_test_utils/__init__.py
nextline_test_utils/py.typed
nextline_test_utils/safe.py
nextline_test_utils/strategies/__init__.py
nextline_test_utils/strategies/datetime.py
nextline_test_utils/strategies/misc.py
nextline_test_utils/strategies/script.py
nextline_test_utils-0.1.2.dist-info/METADATA
nextline_test_utils-0.1.2.dist-info/WHEEL
nextline_test_utils-0.1.2.dist-info/licenses/LICENSE.txt
nextline_test_utils-0.1.2.dist-info/RECORD
